hgf/__init__.py
hgf/app.py
hgf/component.py
hgf/double_buffer.py
hgf/model.py
hgf/gui/__init__.py
hgf/gui/base.py
hgf/gui/button.py
hgf/gui/component.py
hgf/gui/drag.py
hgf/gui/frame.py
hgf/gui/image.py
hgf/gui/menu.py
hgf/gui/structure.py
hgf/gui/switch.py
hgf/gui/text.py
hgf/gui/text_entry.py
hgf/gui/widget.py
hgf/gui/window.py
hgf/timing/__init__.py
hgf/timing/component.py
hgf/timing/gradient.py
hgf/timing/switch.py
hgf/timing/ticker.py
hgf/util/__init__.py
hgf/util/keyboard.py
hgf/util/keys.py
hgf/util/rect.py
hgf/util/timer.py
hgf-0.2.2.dist-info/DESCRIPTION.rst
hgf-0.2.2.dist-info/METADATA
hgf-0.2.2.dist-info/RECORD
hgf-0.2.2.dist-info/WHEEL
hgf-0.2.2.dist-info/metadata.json
hgf-0.2.2.dist-info/top_level.txt
