Metadata-Version: 2.0
Name: hgf
Version: 0.2.2
Summary: A framework for building hierarchical GUIs
Home-page: https://www.github.com/BenFrankel/hgf
Author: Ben Frankel
Author-email: ben.frankel7@gmail.com
License: Apache 2.0
Download-URL: https://www.github.com/BenFrankel/hgf/tarball/0.2.2
Keywords: hgf hierarchical gui framework
Platform: UNKNOWN
Classifier: Development Status :: 2 - Pre-Alpha
Classifier: Intended Audience :: Developers
Classifier: License :: OSI Approved :: Apache Software License
Classifier: Natural Language :: English
Classifier: Operating System :: OS Independent
Classifier: Programming Language :: Python :: 3 :: Only
Classifier: Topic :: Software Development :: Libraries :: Application Frameworks
Classifier: Topic :: Software Development :: Libraries :: pygame
Provides: hgf
Requires-Dist: pygame (>=1.9.1)
Requires-Dist: pyperclip (>=1.6.0)
